rotating_proxy/__init__.py
rotating_proxy/proxy_pool.py
rotating_proxy/proxy_session.py
rotating_proxy-0.3.2.dist-info/licenses/LICENSE
rotating_proxy-0.3.2.dist-info/METADATA
rotating_proxy-0.3.2.dist-info/WHEEL
rotating_proxy-0.3.2.dist-info/top_level.txt
rotating_proxy-0.3.2.dist-info/RECORD
