Metadata-Version: 2.4
Name: rotating_proxy
Version: 0.3.2
Summary: A Python package for managing and using rotating proxies
Author: Will
License: MIT
Project-URL: Homepage, https://github.com/Will6855/rotating-proxy
Classifier: Programming Language :: Python :: 3
Classifier: Programming Language :: Python :: 3.9
Classifier: Programming Language :: Python :: 3.10
Classifier: Programming Language :: Python :: 3.11
Classifier: License :: OSI Approved :: MIT License
Classifier: Operating System :: OS Independent
Classifier: Intended Audience :: Developers
Classifier: Topic :: Internet :: Proxy Servers
Classifier: Topic :: Software Development :: Libraries :: Python Modules
Requires-Python: >=3.9
License-File: LICENSE
Requires-Dist: requests>=2.32.4
Requires-Dist: typing>=3.7.4.3
Requires-Dist: python-dateutil>=2.9.0
Requires-Dist: urllib3>=2.6.0
Requires-Dist: dataclasses>=0.8; python_version < "3.7"
Dynamic: license-file
